{
  "partyList": [
    {
      "name": "Green Ooze",
      "type": "ENEMY",
      "stats": {
        "currentHP": 25,
        "currentMP": 30,
        "maxHP": 25,
        "maxMP": 30,
        "speed": 4,
        "strength": 2,
        "dexterity": 2,
        "intelligence": 2,
        "armourVal": 2,
        "experience": 0,
        "currentLevel": 1,
        "maxLevel": 20
      },
      "skills": [
        5
      ],
      "equipment": {
        "equipSlots": [
          0,
          0,
          0,
          0,
          0
        ]
      },
      "texture": 3
    },
    {
      "name": "Blue Ooze",
      "type": "ENEMY",
      "stats": {
        "currentHP": 25,
        "currentMP": 30,
        "maxHP": 25,
        "maxMP": 30,
        "speed": 4,
        "strength": 2,
        "dexterity": 2,
        "intelligence": 2,
        "armourVal": 2,
        "experience": 0,
        "currentLevel": 1,
        "maxLevel": 20
      },
      "skills": [
        6
      ],
      "equipment": {
        "equipSlots": [
          0,
          0,
          0,
          0,
          0
        ]
      },
      "texture": 2
    },
    {
      "name": "Radiated Duck",
      "type": "ENEMY",
      "stats": {
        "currentHP": 50,
        "currentMP": 30,
        "maxHP": 50,
        "maxMP": 30,
        "speed": 2,
        "strength": 2,
        "dexterity": 2,
        "intelligence": 2,
        "armourVal": 2,
        "experience": 0,
        "currentLevel": 1,
        "maxLevel": 20
      },
      "skills": [
        6
      ],
      "equipment": {
        "equipSlots": [
          0,
          0,
          0,
          0,
          0
        ]
      },
      "texture": 8
    },
    {
      "name": "Poisonous Duck",
      "type": "ENEMY",
      "stats": {
        "currentHP": 50,
        "currentMP": 30,
        "maxHP": 50,
        "maxMP": 30,
        "speed": 2,
        "strength": 2,
        "dexterity": 2,
        "intelligence": 2,
        "armourVal": 2,
        "experience": 21,
        "currentLevel": 2,
        "maxLevel": 20
      },
      "skills": [
        6
      ],
      "equipment": {
        "equipSlots": [
          0,
          0,
          0,
          0,
          0
        ]
      },
      "texture": 7
    },
    {
      "name": "Yellow Ooze",
      "type": "ENEMY",
      "stats": {
        "currentHP": 25,
        "currentMP": 30,
        "maxHP": 25,
        "maxMP": 30,
        "speed": 4,
        "strength": 2,
        "dexterity": 2,
        "intelligence": 2,
        "armourVal": 2,
        "experience": 21,
        "currentLevel": 2,
        "maxLevel": 20
      },
      "skills": [
        6
      ],
      "equipment": {
        "equipSlots": [
          0,
          0,
          0,
          0,
          0
        ]
      },
      "texture": 5
    },
    {
      "name": "Scarred Duck",
      "type": "ENEMY",
      "stats": {
        "currentHP": 50,
        "currentMP": 30,
        "maxHP": 50,
        "maxMP": 30,
        "speed": 3,
        "strength": 2,
        "dexterity": 2,
        "intelligence": 2,
        "armourVal": 2,
        "experience": 21,
        "currentLevel": 2,
        "maxLevel": 20
      },
      "skills": [
        7
      ],
      "equipment": {
        "equipSlots": [
          0,
          0,
          0,
          0,
          0
        ]
      },
      "texture": 11
    },
    {
      "name": "Undead Duck",
      "type": "ENEMY",
      "stats": {
        "currentHP": 60,
        "currentMP": 30,
        "maxHP": 60,
        "maxMP": 30,
        "speed": 0,
        "strength": 2,
        "dexterity": 2,
        "intelligence": 2,
        "armourVal": 2,
        "experience": 36,
        "currentLevel": 3,
        "maxLevel": 20
      },
      "skills": [
        8
      ],
      "equipment": {
        "equipSlots": [
          0,
          0,
          0,
          0,
          0
        ]
      },
      "texture": 13
    },
    {
      "name": "Red Ooze",
      "type": "ENEMY",
      "stats": {
        "currentHP": 50,
        "currentMP": 30,
        "maxHP": 50,
        "maxMP": 30,
        "speed": 3,
        "strength": 2,
        "dexterity": 2,
        "intelligence": 2,
        "armourVal": 2,
        "experience": 36,
        "currentLevel": 3,
        "maxLevel": 20
      },
      "skills": [
        7
      ],
      "equipment": {
        "equipSlots": [
          0,
          0,
          0,
          0,
          0
        ]
      },
      "texture": 4
    },
    {
      "name": "Radiated Scarred Duck",
      "type": "ENEMY",
      "stats": {
        "currentHP": 50,
        "currentMP": 30,
        "maxHP": 50,
        "maxMP": 30,
        "speed": 3,
        "strength": 2,
        "dexterity": 2,
        "intelligence": 2,
        "armourVal": 2,
        "experience": 36,
        "currentLevel": 3,
        "maxLevel": 20
      },
      "skills": [
        7
      ],
      "equipment": {
        "equipSlots": [
          0,
          0,
          0,
          0,
          0
        ]
      },
      "texture": 9
    },
    {
      "name": "Radiated Undead Duck",
      "type": "ENEMY",
      "stats": {
        "currentHP": 50,
        "currentMP": 30,
        "maxHP": 50,
        "maxMP": 30,
        "speed": 3,
        "strength": 2,
        "dexterity": 2,
        "intelligence": 2,
        "armourVal": 2,
        "experience": 51,
        "currentLevel": 4,
        "maxLevel": 20
      },
      "skills": [
        7
      ],
      "equipment": {
        "equipSlots": [
          0,
          0,
          0,
          0,
          0
        ]
      },
      "texture": 11
    },
    {
      "name": "Black Ooze",
      "type": "ENEMY",
      "stats": {
        "currentHP": 50,
        "currentMP": 30,
        "maxHP": 50,
        "maxMP": 30,
        "speed": 3,
        "strength": 2,
        "dexterity": 2,
        "intelligence": 2,
        "armourVal": 2,
        "experience": 51,
        "currentLevel": 4,
        "maxLevel": 20
      },
      "skills": [
        7
      ],
      "equipment": {
        "equipSlots": [
          0,
          0,
          0,
          0,
          0
        ]
      },
      "texture": 7
    },
    {
      "name": "Super Radiated Duck",
      "type": "ENEMY",
      "stats": {
        "currentHP": 50,
        "currentMP": 30,
        "maxHP": 50,
        "maxMP": 30,
        "speed": 3,
        "strength": 2,
        "dexterity": 2,
        "intelligence": 2,
        "armourVal": 2,
        "experience": 51,
        "currentLevel": 4,
        "maxLevel": 20
      },
      "skills": [
        7
      ],
      "equipment": {
        "equipSlots": [
          0,
          0,
          0,
          0,
          0
        ]
      },
      "texture": 8
    },
    {
      "name": "Super Green Ooze",
      "type": "ENEMY",
      "stats": {
        "currentHP": 25,
        "currentMP": 30,
        "maxHP": 25,
        "maxMP": 30,
        "speed": 4,
        "strength": 2,
        "dexterity": 2,
        "intelligence": 2,
        "armourVal": 2,
        "experience": 71,
        "currentLevel": 5,
        "maxLevel": 20
      },
      "skills": [
        5
      ],
      "equipment": {
        "equipSlots": [
          0,
          0,
          0,
          0,
          0
        ]
      },
      "texture": 3
    },
    {
      "name": "Super Blue Ooze",
      "type": "ENEMY",
      "stats": {
        "currentHP": 25,
        "currentMP": 30,
        "maxHP": 25,
        "maxMP": 30,
        "speed": 4,
        "strength": 2,
        "dexterity": 2,
        "intelligence": 2,
        "armourVal": 2,
        "experience": 71,
        "currentLevel": 5,
        "maxLevel": 20
      },
      "skills": [
        6
      ],
      "equipment": {
        "equipSlots": [
          0,
          0,
          0,
          0,
          0
        ]
      },
      "texture": 2
    },
    {
      "name": "Super Radiated Duck",
      "type": "ENEMY",
      "stats": {
        "currentHP": 50,
        "currentMP": 30,
        "maxHP": 50,
        "maxMP": 30,
        "speed": 2,
        "strength": 2,
        "dexterity": 2,
        "intelligence": 2,
        "armourVal": 2,
        "experience": 71,
        "currentLevel": 5,
        "maxLevel": 20
      },
      "skills": [
        6
      ],
      "equipment": {
        "equipSlots": [
          0,
          0,
          0,
          0,
          0
        ]
      },
      "texture": 8
    },
    {
      "name": "Super Poisonous Duck",
      "type": "ENEMY",
      "stats": {
        "currentHP": 50,
        "currentMP": 30,
        "maxHP": 50,
        "maxMP": 30,
        "speed": 2,
        "strength": 2,
        "dexterity": 2,
        "intelligence": 2,
        "armourVal": 2,
        "experience": 96,
        "currentLevel": 6,
        "maxLevel": 20
      },
      "skills": [
        6
      ],
      "equipment": {
        "equipSlots": [
          0,
          0,
          0,
          0,
          0
        ]
      },
      "texture": 7
    },
    {
      "name": "Super Yellow Ooze",
      "type": "ENEMY",
      "stats": {
        "currentHP": 25,
        "currentMP": 30,
        "maxHP": 25,
        "maxMP": 30,
        "speed": 4,
        "strength": 2,
        "dexterity": 2,
        "intelligence": 2,
        "armourVal": 2,
        "experience": 96,
        "currentLevel": 6,
        "maxLevel": 20
      },
      "skills": [
        6
      ],
      "equipment": {
        "equipSlots": [
          0,
          0,
          0,
          0,
          0
        ]
      },
      "texture": 5
    },
    {
      "name": "Super Scarred Duck",
      "type": "ENEMY",
      "stats": {
        "currentHP": 50,
        "currentMP": 30,
        "maxHP": 50,
        "maxMP": 30,
        "speed": 3,
        "strength": 2,
        "dexterity": 2,
        "intelligence": 2,
        "armourVal": 2,
        "experience": 96,
        "currentLevel": 6,
        "maxLevel": 20
      },
      "skills": [
        7
      ],
      "equipment": {
        "equipSlots": [
          0,
          0,
          0,
          0,
          0
        ]
      },
      "texture": 11
    },
    {
      "name": "Super Undead Duck",
      "type": "ENEMY",
      "stats": {
        "currentHP": 60,
        "currentMP": 30,
        "maxHP": 60,
        "maxMP": 30,
        "speed": 0,
        "strength": 2,
        "dexterity": 2,
        "intelligence": 2,
        "armourVal": 2,
        "experience": 126,
        "currentLevel": 7,
        "maxLevel": 20
      },
      "skills": [
        8
      ],
      "equipment": {
        "equipSlots": [
          0,
          0,
          0,
          0,
          0
        ]
      },
      "texture": 13
    },
    {
      "name": "Super Red Ooze",
      "type": "ENEMY",
      "stats": {
        "currentHP": 50,
        "currentMP": 30,
        "maxHP": 50,
        "maxMP": 30,
        "speed": 3,
        "strength": 2,
        "dexterity": 2,
        "intelligence": 2,
        "armourVal": 2,
        "experience": 126,
        "currentLevel":7,
        "maxLevel": 20
      },
      "skills": [
        7
      ],
      "equipment": {
        "equipSlots": [
          0,
          0,
          0,
          0,
          0
        ]
      },
      "texture": 4
    },
    {
      "name": "Super Radiated Scarred Duck",
      "type": "ENEMY",
      "stats": {
        "currentHP": 50,
        "currentMP": 30,
        "maxHP": 50,
        "maxMP": 30,
        "speed": 3,
        "strength": 2,
        "dexterity": 2,
        "intelligence": 2,
        "armourVal": 2,
        "experience": 126,
        "currentLevel": 7,
        "maxLevel": 20
      },
      "skills": [
        7
      ],
      "equipment": {
        "equipSlots": [
          0,
          0,
          0,
          0,
          0
        ]
      },
      "texture": 9
    },
    {
      "name": "Super Radiated Undead Duck",
      "type": "ENEMY",
      "stats": {
        "currentHP": 50,
        "currentMP": 30,
        "maxHP": 50,
        "maxMP": 30,
        "speed": 3,
        "strength": 2,
        "dexterity": 2,
        "intelligence": 2,
        "armourVal": 2,
        "experience": 161,
        "currentLevel": 8,
        "maxLevel": 20
      },
      "skills": [
        7
      ],
      "equipment": {
        "equipSlots": [
          0,
          0,
          0,
          0,
          0
        ]
      },
      "texture": 10
    },
    {
      "name": "Super Black Ooze",
      "type": "ENEMY",
      "stats": {
        "currentHP": 50,
        "currentMP": 30,
        "maxHP": 50,
        "maxMP": 30,
        "speed": 3,
        "strength": 2,
        "dexterity": 2,
        "intelligence": 2,
        "armourVal": 2,
        "experience": 161,
        "currentLevel": 8,
        "maxLevel": 20
      },
      "skills": [
        7
      ],
      "equipment": {
        "equipSlots": [
          0,
          0,
          0,
          0,
          0
        ]
      },
      "texture": 6
    },
    {
      "name": "Super Super Radiated Duck",
      "type": "ENEMY",
      "stats": {
        "currentHP": 50,
        "currentMP": 30,
        "maxHP": 50,
        "maxMP": 30,
        "speed": 3,
        "strength": 2,
        "dexterity": 2,
        "intelligence": 2,
        "armourVal": 2,
        "experience": 161,
        "currentLevel": 8,
        "maxLevel": 20
      },
      "skills": [
        7
      ],
      "equipment": {
        "equipSlots": [
          0,
          0,
          0,
          0,
          0
        ]
      },
      "texture": 12
    },
  ],
  "consumables": [
    0,
    1,
    2
  ],
  "equipment": [
    1
  ]
}
